Metadata-Version: 2.1
Name: wheelz
Version: 0.1
Summary: wheelz -- complexity via Burrows-Wheeler transform.
Home-page: http://github.com/ncgr/wheelz
Author: Joel Berendzen
Author-email: joelb@ncgr.org
Maintainer: Joel Berendzen
Maintainer-email: joelb@ncgr.org
License: BSD 3-Clause License
Keywords: science,biology,bioinformatics,genomics,genes,genomes,proteomes,complexity,Burrows-Wheeler transform,distribution,proteins,peptides,nucleic acids
Platform: UNKNOWN
Classifier: Development Status :: 5 - Production/Stable
Classifier: Environment :: Console
Classifier: Framework :: Flask
Classifier: Intended Audience :: Science/Research
Classifier: License :: OSI Approved :: BSD License
Classifier: Operating System :: MacOS :: MacOS X
Classifier: Operating System :: POSIX :: Linux
Classifier: Operating System :: POSIX :: BSD
Classifier: Programming Language :: Python :: 3.5
Classifier: Programming Language :: Python :: 3.6
Classifier: Programming Language :: Python :: 3.7
Classifier: Programming Language :: Python :: 3.8
Classifier: Programming Language :: C
Classifier: Topic :: Scientific/Engineering :: Bio-Informatics
Provides-Extra: docs
Provides-Extra: tests
Provides-Extra: all
